rl4net/__init__.py
rl4net/__version__.py
rl4net/agents/DDPG_base.py
rl4net/agents/DQN_base.py
rl4net/agents/Linear_base.py
rl4net/agents/__init__.py
rl4net/envs/__init__.py
rl4net/envs/findtreasure_env.py
rl4net/envs/maze_env.py
rl4net/envs/PowerControl/PC_env.py
rl4net/envs/PowerControl/PC_env_format_test.py
rl4net/envs/PowerControl/PC_env_origin.py
rl4net/envs/PowerControl/PC_env_unit_test.py
rl4net/envs/PowerControl/__init__.py
rl4net/envs/power_allocation/__init__.py
rl4net/envs/power_allocation/pa_env.py
rl4net/envs/power_allocation/pa_rb_env.py
rl4net/envs/power_allocation/pa_rb_utils.py
rl4net/envs/power_allocation/test_pa_env.py
rl4net/envs/power_allocation/test_pa_rb_env.py
rl4net/logs/__init__.py
rl4net/logs/assamble.py
rl4net/models/__init__.py
rl4net/models/actor_net.py
rl4net/models/critic_net.py
rl4net/models/dqn_net.py
rl4net/utils/OUProcess.py
rl4net/utils/ReplayBuffer.py
rl4net/utils/__init__.py
rl4net/utils/config.py
rl4net/utils/update.py
rl4net-0.2.6.dist-info/LICENCE
rl4net-0.2.6.dist-info/METADATA
rl4net-0.2.6.dist-info/WHEEL
rl4net-0.2.6.dist-info/top_level.txt
rl4net-0.2.6.dist-info/RECORD
